mvf/__init__.py
mvf/cli/__init__.py
mvf/cli/cli.py
mvf/cli/utils.py
mvf/dag/__init__.py
mvf/dag/builder.py
mvf/integration/__init__.py
mvf/integration/mvf_config.py
mvf/integration/config/__init__.py
mvf/integration/config/fit_model.py
mvf/integration/config/predict_model.py
mvf/integration/config/preprocess_data.py
mvf/integration/config/split_data.py
mvf/integration/config/validate.py
mvf/integration/config/validate_model.py
mvf/integration/process/__init__.py
mvf/integration/process/fit_model.py
mvf/integration/process/predict_model.py
mvf/integration/process/preprocess_data.py
mvf/integration/process/split_data.py
mvf/process/__init__.py
mvf/process/fit_model.py
mvf/process/predict_model.py
mvf/process/split_data.py
mvf/process/utils.py
mvf/process/validate.py
mvf/process/validate_model.py
mvf/process/validation.py
mvf/template/__init__.py
mvf/template/config.py
mvf/template/file_gen.py
mvf/template/templates/__init__.py
mvf/template/templates/models_py.py
mvf/template/templates/models_r.py
mvf/template/templates/preprocess.py
mvf-0.0.18.dist-info/LICENSE
mvf-0.0.18.dist-info/METADATA
mvf-0.0.18.dist-info/WHEEL
mvf-0.0.18.dist-info/entry_points.txt
mvf-0.0.18.dist-info/top_level.txt
mvf-0.0.18.dist-info/RECORD
