Metadata-Version: 2.1
Name: mvf
Version: 0.0.18
Summary: A package implementing a supervised learning model validation framework.
Home-page: UNKNOWN
Author: Tom Kim
Author-email: tom.kim@certus-tech.com
License: UNKNOWN
Keywords: python,R,machine learning,validation,framework
Platform: UNKNOWN
Classifier: Programming Language :: Python :: 3.9
Classifier: Framework :: Jupyter
Classifier: License :: Free For Educational Use
Classifier: Operating System :: Unix
Requires-Python: >=3.9
License-File: LICENSE
Requires-Dist: click
Requires-Dist: feather-format
Requires-Dist: matplotlib
Requires-Dist: pandas
Requires-Dist: ploomber
Requires-Dist: rpy2
Requires-Dist: rpy2-r6
Requires-Dist: schema
Requires-Dist: scikit-learn
Provides-Extra: dev
Requires-Dist: coverage ; extra == 'dev'
Requires-Dist: pytest ; extra == 'dev'
Requires-Dist: testbook ; extra == 'dev'
Requires-Dist: twine ; extra == 'dev'
